LICENSE
docs/index.md
pmpm/__init__.py
pmpm/core.py
pmpm/env_variant_generator.py
pmpm/packages/__init__.py
pmpm/packages/conda.py
pmpm/packages/libmadam.py
pmpm/packages/toast.py
pmpm/util.py
python_pmpm-0.2.0.dist-info/LICENSE
python_pmpm-0.2.0.dist-info/METADATA
python_pmpm-0.2.0.dist-info/WHEEL
python_pmpm-0.2.0.dist-info/entry_points.txt
python_pmpm-0.2.0.dist-info/RECORD
